AUTHORS.rst
CONTRIBUTING.rst
HISTORY.rst
LICENSE
MANIFEST.in
README.rst
requirements_dev.txt
requirements_prod.txt
setup.cfg
setup.py
docs/Makefile
docs/authors.rst
docs/conf.py
docs/contributing.rst
docs/history.rst
docs/index.rst
docs/installation.rst
docs/make.bat
docs/readme.rst
docs/usage.rst
ghgh/__init__.py
ghgh/ghgh.py
ghgh.egg-info/PKG-INFO
ghgh.egg-info/SOURCES.txt
ghgh.egg-info/dependency_links.txt
ghgh.egg-info/not-zip-safe
ghgh.egg-info/top_level.txt
tests/test_ghgh.py