Metadata-Version: 1.1
Name: ghgh
Version: 0.1.1
Summary: None
Home-page: https://github.com/huntzhan/ghgh
Author: Hunt Zhan
Author-email: huntzhan.dev@gmail.com
License: MIT license
Keywords: ghgh
Platform: UNKNOWN
Classifier: Development Status :: 2 - Pre-Alpha
Classifier: Intended Audience :: Developers
Classifier: License :: OSI Approved :: MIT License
Classifier: Natural Language :: English
Classifier: Programming Language :: Python :: 3
Classifier: Programming Language :: Python :: 3.6
Classifier: Programming Language :: Python :: 3.7
